MANIFEST.in
README.md
grove.py
setup.py
python_grove.egg-info/PKG-INFO
python_grove.egg-info/SOURCES.txt
python_grove.egg-info/dependency_links.txt
python_grove.egg-info/top_level.txt